bites/__init__.py
bites/_bs.py
bites-0.0.10.dist-info/LICENSE
bites-0.0.10.dist-info/METADATA
bites-0.0.10.dist-info/WHEEL
bites-0.0.10.dist-info/top_level.txt
bites-0.0.10.dist-info/RECORD
