Metadata-Version: 2.1
Name: bites
Version: 0.0.10
Summary: Operating bytes made easy
Home-page: https://github.com/djosix/bites
Author: djosix
Author-email: toregenerate@gmail.com
License: UNKNOWN
Platform: UNKNOWN
Classifier: Programming Language :: Python :: 3
Classifier: License :: OSI Approved :: MIT License
